jack_spam/__init__.py
jack_spam/spam_sender.py
jack_email_spam-0.1.0.dist-info/METADATA
jack_email_spam-0.1.0.dist-info/WHEEL
jack_email_spam-0.1.0.dist-info/top_level.txt
jack_email_spam-0.1.0.dist-info/RECORD
