Metadata-Version: 2.4
Name: jack-email-spam
Version: 0.1.0
Summary: Email automation/testing utilities (educational / legitimate use only).
Home-page: https://github.com/yourusername/jack-email-spam
Author: Your Name
Author-email: your.email@example.com
License: MIT
Classifier: Programming Language :: Python :: 3
Classifier: Operating System :: OS Independent
Requires-Python: >=3.6
Requires-Dist: requests
Requires-Dist: user-agent
Requires-Dist: pyfiglet
Requires-Dist: rich
Dynamic: author
Dynamic: author-email
Dynamic: classifier
Dynamic: description
Dynamic: description-content-type
Dynamic: home-page
Dynamic: license
Dynamic: requires-dist
Dynamic: requires-python
Dynamic: summary
